ape_llamanodes/__init__.py
ape_llamanodes/provider.py
ape_llamanodes/py.typed
ape_llamanodes-0.6.1.dist-info/LICENSE
ape_llamanodes-0.6.1.dist-info/METADATA
ape_llamanodes-0.6.1.dist-info/WHEEL
ape_llamanodes-0.6.1.dist-info/top_level.txt
ape_llamanodes-0.6.1.dist-info/RECORD
